{
  "users": [
    {
      "id": "1",
      "name": "kevin",
      "email": "kevinapple157@gmail.com",
      "paasword": "123"
    },
    {
      "id": "2",
      "name": "yash",
      "email": "yashapple157@gmail.com",
      "paasword": "789"
    },
    {
      "id": "afe4",
      "name": "kj",
      "email": "kevinapple157@gmail.com123",
      "password": "11"
    },
    {
      "id": "1397",
      "name": "kevin",
      "email": "kevinapple157@gmail.com123",
      "password": "123"
    },
    {
      "id": "7",
      "name": "kevin",
      "email": "k@gmail.com",
      "password": "999"
    },
    {
      "id": "2765",
      "name": "b",
      "email": "b@gmail.com",
      "password": "b111"
    },
    {
      "id": "247c",
      "name": "a",
      "email": "a@gmail.com",
      "password": "111"
    }
  ],
  "contact": [
    {
      "id": "115d",
      "name": "hhh",
      "number": "3333333333",
      "userId": "1"
    },
    {
      "id": "e648",
      "name": "jjjj",
      "number": "12333333",
      "userId": "7"
    },
    {
      "id": "e648",
      "name": "jjjj",
      "number": "12333333",
      "userId": "7"
    },
    {
      "id": "e648",
      "name": "jjjj",
      "number": "12333333",
      "userId": "7"
    },
    {
      "id": "e648",
      "name": "AAAA",
      "number": "12333333",
      "userId": "7"
    },
    {
      "id": "100e",
      "name": "kevin",
      "number": "1478956230",
      "userId": "7"
    },
    {
      "id": "d691",
      "name": "kevvibn",
      "number": "48554252125",
      "userId": "7"
    },
    {
      "id": "78db",
      "name": "kevin",
      "number": "7894561230",
      "userId": "7"
    },
    {
      "id": "1cf7",
      "name": "kevin",
      "number": "7894561230",
      "userId": "7"
    },
    {
      "id": "59a3",
      "name": "kevin",
      "number": "1478956230",
      "userId": "7"
    },
    {
      "id": "0b23",
      "name": "",
      "number": "",
      "userId": "7"
    },
    {
      "id": "c465",
      "name": "bbbb",
      "number": "2222",
      "userId": "247c"
    }
  ]
}